pyzotero/__init__.py
pyzotero/zotero.py
pyzotero/zotero_errors.py
test/__init__.py
test/test_zotero.py
test/api_responses/__init__.py
pyzotero3-1.4.25.dist-info/AUTHORS
pyzotero3-1.4.25.dist-info/METADATA
pyzotero3-1.4.25.dist-info/WHEEL
pyzotero3-1.4.25.dist-info/top_level.txt
pyzotero3-1.4.25.dist-info/RECORD
