Metadata-Version: 2.1
Name: pyzotero3
Version: 1.4.25
Summary: Python 3 wrapper for the Zotero API
Home-page: https://github.com/rsalmaso/pyzotero3
Author: Stephan Hügel
Author-email: urschrei@gmail.com
Maintainer: Raffaele Salmaso
Maintainer-email: raffaele.salmaso@gmail.com
License: MIT License
Download-URL: https://github.com/rsalmaso/pyzotero3/tarball/v1.4.25
Keywords: zotero
Platform: UNKNOWN
Classifier: Programming Language :: Python
Classifier: Programming Language :: Python :: 3.6
Classifier: Programming Language :: Python :: 3.7
Classifier: Programming Language :: Python :: 3.8
Classifier: Programming Language :: Python :: 3.9
Classifier: Programming Language :: Python :: 3.10
Classifier: Development Status :: 5 - Production/Stable
Classifier: Intended Audience :: Developers
Classifier: Intended Audience :: Education
Classifier: License :: OSI Approved :: MIT License
Classifier: Operating System :: OS Independent
Classifier: Topic :: Software Development :: Libraries :: Python Modules
Requires-Dist: feedparser
Requires-Dist: pytz
Requires-Dist: requests (>=2.21.0)
Requires-Dist: bibtexparser
